{
	"name": "powerquery2",
	"properties": {
		"type": "WranglingDataFlow",
		"typeProperties": {
			"sources": [
				{
					"name": "MoviesCSV",
					"script": "source(allowSchemaDrift: true,\n\tvalidateSchema: false,\n\tignoreNoFilesFound: false) ~>  MoviesCSV",
					"dataset": {
						"referenceName": "MoviesCSV",
						"type": "DatasetReference"
					}
				}
			],
			"script": "section Section1;\r\nshared MoviesCSV = let AdfDoc = AzureStorage.BlobContents(\"https://depstact.blob.core.windows.net/input/movies.csv\"),Csv = Csv.Document(AdfDoc, [Delimiter = \",\", Encoding = TextEncoding.Utf8, QuoteStyle = QuoteStyle.Csv]), PromotedHeaders = Table.PromoteHeaders(Csv, [PromoteAllScalars = true]) in  PromotedHeaders;\r\nshared UserQuery = let Source = #\"MoviesCSV\" in Source;\r\n",
			"documentLocale": "en-us"
		}
	}
}